reComputer/__init__.py
reComputer/main.py
reComputer-0.0.1.data/data/scripts/run.sh
reComputer-0.0.1.dist-info/LICENSE
reComputer-0.0.1.dist-info/METADATA
reComputer-0.0.1.dist-info/WHEEL
reComputer-0.0.1.dist-info/top_level.txt
reComputer-0.0.1.dist-info/RECORD
