Metadata-Version: 2.1
Name: reComputer
Version: 0.0.1
Summary: run AI on Jetson, all you need is reComputer
Author-email: luozhixin <zhixin.luo@seeed.cc>
Project-URL: Homepage, https://github.com/Seeed-Projects/jetson-examples
Project-URL: Issues, https://github.com/Seeed-Projects/jetson-examples/issues
Classifier: Programming Language :: Python :: 3
Classifier: License :: OSI Approved :: MIT License
Classifier: Operating System :: OS Independent
Requires-Python: >=3.8
License-File: LICENSE
